gemba/__init__.py
gemba/gemba_da.py
gemba/gemba_esa.py
gemba/gemba_mqm_utils.py
gemba/gpt_api.py
gemba/mtme_tools.py
gemba/prompt.py
gemba/scores.py
gemba/testset.py
gemba/utils.py
gemba-0.1.3.dist-info/METADATA
gemba-0.1.3.dist-info/WHEEL
gemba-0.1.3.dist-info/licenses/LICENSE.md
gemba-0.1.3.dist-info/RECORD
