Metadata-Version: 2.4
Name: gemba
Version: 0.1.3
Summary: GEMBA — GPT Estimation Metric Based Assessment
Project-URL: Homepage, https://github.com/joelniklaus/gemba
Author-email: Joel Niklaus <joel@niklaus.ai>
License-Expression: MIT
License-File: LICENSE.md
Classifier: License :: OSI Approved :: MIT License
Classifier: Operating System :: OS Independent
Classifier: Programming Language :: Python :: 3
Requires-Python: >=3.8
Requires-Dist: absl-py
Requires-Dist: diskcache
Requires-Dist: ipdb
Requires-Dist: openai>=1.0.0
Requires-Dist: pandas
Requires-Dist: pexpect
Requires-Dist: scipy
Requires-Dist: termcolor
